pytenor
