Metadata-Version: 2.1
Name: pytenor
Version: 1.1
Summary: A simple API wrapper for tenor's gif api that is built with asyncio.
Home-page: https://github.com/bossauh/pytenor
Author: Philippe Mathew
Author-email: philmattdev@gmail.com
License: MIT
Download-URL: https://github.com/bossauh/pytenor/archive/refs/tags/v1_1.tar.gz
Keywords: api,tools,utilities
Platform: UNKNOWN
Classifier: Development Status :: 5 - Production/Stable
Classifier: Intended Audience :: Developers
Classifier: Topic :: Software Development :: Build Tools
Classifier: License :: OSI Approved :: MIT License
Classifier: Programming Language :: Python :: 3.6
Classifier: Programming Language :: Python :: 3.7
License-File: LICENSE
